LICENSE
MANIFEST.in
README.md
requirements.txt
setup.cfg
setup.py
lastpass_python_cli/__init__.py
lastpass_python_cli/__main__.py
lastpass_python_cli.egg-info/PKG-INFO
lastpass_python_cli.egg-info/SOURCES.txt
lastpass_python_cli.egg-info/dependency_links.txt
lastpass_python_cli.egg-info/entry_points.txt
lastpass_python_cli.egg-info/requires.txt
lastpass_python_cli.egg-info/top_level.txt
lastpass_python_cli.egg-info/zip-safe