Metadata-Version: 2.1
Name: lastpass-python-cli
Version: 1.0.3
Summary: Lastpass Python CLI
Home-page: https://github.com/guilt/lastpass-python-cli
Author: Karthik Kumar Viswanathan
Author-email: karthikkumar@gmail.com
License: MIT
Keywords: lastpass,cli,lpass
Platform: UNKNOWN
Classifier: License :: OSI Approved :: MIT License
Classifier: Intended Audience :: Developers
Classifier: Programming Language :: Python
Classifier: Programming Language :: Python :: 2.7
Classifier: Programming Language :: Python :: 3.6
Classifier: Programming Language :: Python :: 3.7
Classifier: Programming Language :: Python :: 3.8
